<?xml version="1.0" encoding="utf-8"?>
<settings>
  <source-db>
    <type>oracle</type>
    <conn>Data Source=(DESCRIPTION=(ADDRESS=(PROTOCOL=TCP)(HOST=10.35.63.143)(PORT=1521))(CONNECT_DATA=(SERVICE_NAME = cmadb)));User Id=cne;Password=cne;Unicode=True;</conn>
  </source-db>
  <destination-db>
    <type>oracle</type>
    <conn>Data Source=(DESCRIPTION=(ADDRESS=(PROTOCOL=TCP)(HOST=10.35.63.24)(PORT=1521))(CONNECT_DATA=(SERVICE_NAME = cmadb)));User Id=cne;Password=cne;Unicode=True;</conn>
  </destination-db>
  <sql-command-timeout>1800</sql-command-timeout>

  <mappings>
    <table-mapping source="NationalBureau" destination="NationalBureau"  isSync="true"  isKeepObsoleteDestinationData="true">
      <column-mapping source="ID" destination="ID" isKey="true" isImmutableKey="true"/>
      <column-mapping source="ProductName" destination="ProductName"/>
      <column-mapping source="Area" destination="Area"/>
      <column-mapping source="CollectName" destination="CollectName"/>
      <column-mapping source="Unit" destination="Unit"/>
      <column-mapping source="ProductPrice" destination="ProductPrice"/>
      <column-mapping source="ReportDate" destination="ReportDate"/>
      <column-mapping source="CreateDate" destination="CreateDate"/>
      <filter>
        <![CDATA[ CreateDate > TO_DATE({FromTime}, 'mm/dd/yyyy:hh:mi:ssam') AND CreateDate <= TO_DATE({CurrentSyncTime}, 'mm/dd/yyyy:hh:mi:ssam')]]>
      </filter>
    </table-mapping>
  </mappings>

  <post-sync-tasks>
  </post-sync-tasks>

  <custom-bonds>
  </custom-bonds>
</settings>


